MANIFEST.in
setup.py
minimumTFTP/minimumTFTP.py
minimumTFTP.egg-info/PKG-INFO
minimumTFTP.egg-info/SOURCES.txt
minimumTFTP.egg-info/dependency_links.txt
minimumTFTP.egg-info/top_level.txt