Metadata-Version: 1.0
Name: minimumTFTP
Version: 20110917
Summary: tftp server and client.
Home-page: UNKNOWN
Author: shigekiyamada
Author-email: yam@tokyo.email.ne.jp
License: BSD
Keywords: network,internet,tftp
Platform: UNKNOWN
Classifier: Development Status :: 3 - Alpha
Classifier: License :: OSI Approved :: BSD License
Classifier: Programming Language :: Python :: 3
Classifier: Topic :: Internet
Classifier: Environment :: Console
